simpldlogger/__init__.py
simpldlogger/datalogger.py
simpldlogger-1.3.0.dist-info/METADATA
simpldlogger-1.3.0.dist-info/WHEEL
simpldlogger-1.3.0.dist-info/licenses/LICENSE
simpldlogger-1.3.0.dist-info/RECORD
