Metadata-Version: 2.1
Name: simpldlogger
Version: 1.3.0
Summary: Package that provides an easy API for logging different types of events that have occurred.
Project-URL: Homepage, https://github.com/MateuszFerenc/my_pythons/tree/main/data_logger
Project-URL: Bug Tracker, https://github.com/MateuszFerenc/my_pythons/issues
Author-email: Mateusz Ferenc <ferenc.mateusz.priv@gmail.com>
Maintainer-email: Mateusz Ferenc <ferenc.mateusz.priv@gmail.com>
License: MIT License
License-File: LICENSE
Keywords: data logger,logging
Classifier: License :: OSI Approved :: MIT License
Classifier: Operating System :: OS Independent
Classifier: Programming Language :: Python :: 3
Requires-Python: >=3.8
